{
  "CardID": 2781307,
  "CustomDeck": {
    "27813": {
      "BackIsHidden": true,
      "BackURL": "https://steamusercontent-a.akamaihd.net/ugc/2342503777940352139/A2D42E7E5C43D045D72CE5CFC907E4F886C8C690/",
      "FaceURL": "https://steamusercontent-a.akamaihd.net/ugc/14424572945060855941/88EAEFED2981F6738C81BA1F04EA2D00A76679BC/",
      "NumHeight": 3,
      "NumWidth": 10,
      "Type": 0
    }
  },
  "GMNotes": "{\"id\": \"04191\"}",
  "GUID": "bb2e3f",
  "Name": "Card",
  "Nickname": "古代遗物",
  "Transform": {
    "rotY": 180,
    "rotZ": 180,
    "scaleX": 1,
    "scaleY": 1,
    "scaleZ": 1
  }
}