{
  "CardID": 452202,
  "CustomDeck": {
    "4522": {
      "BackIsHidden": true,
      "BackURL": "https://steamusercontent-a.akamaihd.net/ugc/2342503777940352139/A2D42E7E5C43D045D72CE5CFC907E4F886C8C690/",
      "FaceURL": "https://steamusercontent-a.akamaihd.net/ugc/18322457102117966504/20C92CB4B34DCE613736EF8E2977C0F20151184C/",
      "NumHeight": 2,
      "NumWidth": 5,
      "Type": 0,
      "UniqueBack": false
    }
  },
  "Description": "Вещь. Оружие. Огнестрельное.",
  "GMNotes_path": "LanguagePackRussian-Campaigns.RussianC/EdgeoftheEarth.895eaa/КольтСухаря32-гокалибра.07590a.gmnotes",
  "GUID": "07590a",
  "Name": "Card",
  "Nickname": "Кольт Сухаря 32-го калибра",
  "Tags": [
    "Asset",
    "PlayerCard"
  ],
  "Transform": {
    "posX": 28.057,
    "posY": 2.138,
    "posZ": 31.378,
    "rotX": 0,
    "rotY": 270,
    "rotZ": 0,
    "scaleX": 1,
    "scaleY": 1,
    "scaleZ": 1
  }
}
