{
  "CardID": 105500,
  "CustomDeck": {
    "1055": {
      "BackIsHidden": true,
      "BackURL": "https://steamusercontent-a.akamaihd.net/ugc/2342503777940352139/A2D42E7E5C43D045D72CE5CFC907E4F886C8C690/",
      "FaceURL": "https://steamusercontent-a.akamaihd.net/ugc/25426501412295819/AA9A046193E17045184A994284E2DD20D388648E/",
      "NumHeight": 1,
      "NumWidth": 1,
      "Type": 0
    }
  },
  "GMNotes_path": "BaldursGateIII.995e96/5eClassSubclass.312dd8/CarefulSpell.e0004a.gmnotes",
  "GUID": "e0004a",
  "Name": "Card",
  "Nickname": "Careful Spell",
  "Tags": [
    "PlayerCard"
  ],
  "Transform": {
    "rotY": 270,
    "scaleX": 1,
    "scaleY": 1,
    "scaleZ": 1
  }
}
