{
  "CardID": 125700,
  "CustomDeck": {
    "1257": {
      "BackIsHidden": true,
      "BackURL": "https://steamusercontent-a.akamaihd.net/ugc/2342503777940351785/F64D8EFB75A9E15446D24343DA0A6EEF5B3E43DB/",
      "FaceURL": "https://steamusercontent-a.akamaihd.net/ugc/9366247043036114562/0122C29F72098685A4A16BF85D9DC04C6B158A4A/",
      "NumHeight": 1,
      "NumWidth": 1,
      "Type": 0,
      "UniqueBack": true
    }
  },
  "GMNotes": "{\n  \"id\": \"67d746d1-c825-4031-9614-c31bcc00bf4f\"\n}",
  "GUID": "b2fbec",
  "Name": "Card",
  "Nickname": "Cornered Rat",
  "Transform": {
    "rotY": 270,
    "rotZ": 180,
    "scaleX": 1,
    "scaleY": 1,
    "scaleZ": 1
  }
}
