{
  "CardID": 267600,
  "CustomDeck": {
    "2676": {
      "BackIsHidden": true,
      "BackURL": "https://steamusercontent-a.akamaihd.net/ugc/18100331731042679942/ACE06806C225CFC35C2DB03607002A3689AF8FD7/",
      "FaceURL": "https://steamusercontent-a.akamaihd.net/ugc/13710434056426264681/CEDFC59591DC0A2FB0E96B06EFB85CB4534CE162/",
      "NumHeight": 1,
      "NumWidth": 1,
      "Type": 0,
      "UniqueBack": true
    }
  },
  "GMNotes": "{\n  \"id\": \"c74726a4-56d0-425d-af6c-86c53b3ea317\"\n}",
  "GUID": "83feae",
  "Name": "Card",
  "Nickname": "Cyclopean Acropolis",
  "Snap": false,
  "Transform": {
    "rotY": 90,
    "rotZ": 180,
    "scaleX": 1,
    "scaleY": 1,
    "scaleZ": 1
  }
}
