{
  "CardID": 110300,
  "CustomDeck": {
    "1103": {
      "BackIsHidden": true,
      "BackURL": "https://steamusercontent-a.akamaihd.net/ugc/13096979591958888458/4A94DD07CBB7F780F3D2F01997C71276DBFA0B7B/",
      "FaceURL": "https://steamusercontent-a.akamaihd.net/ugc/17887889190091520274/3794A608A08CC73C324688CCD223AF95E4179770/",
      "NumHeight": 1,
      "NumWidth": 1,
      "Type": 0,
      "UniqueBack": true
    }
  },
  "GMNotes": "{\n  \"id\": \"dc941a22-f9bd-4367-b8dc-7bba1b5deabb\"\n}",
  "GUID": "25fd5b",
  "Name": "Card",
  "Nickname": "Twisted Caldera",
  "Transform": {
    "rotY": 270,
    "scaleX": 1,
    "scaleY": 1,
    "scaleZ": 1
  }
}
