{
  "CardID": 801200,
  "CustomDeck": {
    "8012": {
      "BackIsHidden": true,
      "BackURL": "https://steamusercontent-a.akamaihd.net/ugc/14420325627665204237/8095A2502E3764076F1D1402BC2383ADCCDEA48C/",
      "FaceURL": "https://steamusercontent-a.akamaihd.net/ugc/15470035744427567257/7B618057D1756B99AC6A923C19A2550581028872/",
      "NumHeight": 1,
      "NumWidth": 1,
      "Type": 0,
      "UniqueBack": true
    }
  },
  "GMNotes": "{\n  \"id\": \"675487c5-106f-47e9-91a7-0419c9f9d559\"\n}",
  "GUID": "e00001",
  "Name": "Card",
  "Nickname": "Adam Madaras...?",
  "Transform": {
    "rotY": 270,
    "scaleX": 1,
    "scaleY": 1,
    "scaleZ": 1
  }
}
