{
  "CardID": 8045500,
  "CustomDeck": {
    "80455": {
      "BackIsHidden": true,
      "BackURL": "https://steamusercontent-a.akamaihd.net/ugc/2342503777940351785/F64D8EFB75A9E15446D24343DA0A6EEF5B3E43DB/",
      "FaceURL": "https://steamusercontent-a.akamaihd.net/ugc/13739145715103394756/D96A299ED61FB9BE3A9647421ABE0E851DBFB0B7/",
      "NumHeight": 1,
      "NumWidth": 1,
      "Type": 0
    }
  },
  "GMNotes": "{\n  \"id\": \"389fe0d2-8053-4bcd-a55a-685fde0b9619\"\n}",
  "GUID": "e00005",
  "Name": "Card",
  "Nickname": "Selenian Evils",
  "Transform": {
    "rotY": 270,
    "scaleX": 1,
    "scaleY": 1,
    "scaleZ": 1
  }
}
