{
  "CardID": 3722,
  "CustomDeck": {
    "37": {
      "BackIsHidden": true,
      "BackURL": "https://steamusercontent-a.akamaihd.net/ugc/2342503777940351785/F64D8EFB75A9E15446D24343DA0A6EEF5B3E43DB/",
      "FaceURL": "https://steamusercontent-a.akamaihd.net/ugc/11438415744914971500/6705822A85B22954CE87B6922B931BCC110AC2E0/",
      "NumHeight": 7,
      "NumWidth": 10,
      "Type": 0,
      "UniqueBack": false
    }
  },
  "Description": "Колдовство.",
  "GMNotes": "{\n  \"id\": \"82035\"\n}",
  "GUID": "32a6e2",
  "Name": "Card",
  "Nickname": "Под гипнозом",
  "Tags": [
    "ScenarioCard"
  ],
  "Transform": {
    "rotY": 270,
    "scaleX": 1,
    "scaleY": 1,
    "scaleZ": 1
  }
}
