{
  "CardID": 100300,
  "CustomDeck": {
    "1003": {
      "BackIsHidden": true,
      "BackURL": "https://i.imgur.com/9eNQB00.jpg",
      "FaceURL": "https://i.imgur.com/LU4KMXd.jpg",
      "NumHeight": 1,
      "NumWidth": 1,
      "Type": 0,
      "UniqueBack": true
    }
  },
  "Description": "Runesmith Caryll Instruction Hall",
  "GMNotes_path": "Bloodborne-CityoftheUnseen.64cc4a/4TheFrailtyofMen.4117f5/LectureHall.e00004.gmnotes",
  "GUID": "e00004",
  "Name": "Card",
  "Nickname": "Lecture Hall",
  "Tags": [
    "Location",
    "ScenarioCard"
  ],
  "Transform": {
    "rotY": 270,
    "scaleX": 1,
    "scaleY": 1,
    "scaleZ": 1
  }
}
