{
  "CardID": 1299800,
  "CustomDeck": {
    "12998": {
      "BackIsHidden": true,
      "BackURL": "https://steamusercontent-a.akamaihd.net/ugc/13639189875377045559/DC393A8772700B83E14113DCF89D0F277AA0FB26/",
      "FaceURL": "https://steamusercontent-a.akamaihd.net/ugc/13898816233721774680/C53E62CF4AEAAA5FAFC0AD8C29EA96BD8FA38962/",
      "NumHeight": 1,
      "NumWidth": 1,
      "Type": 0,
      "UniqueBack": true
    }
  },
  "Description": "Инсмут. Городской центр.",
  "GMNotes": "{\n  \"id\": \"07137\"\n}",
  "GUID": "237c9f",
  "Name": "Card",
  "Nickname": "Бакалейная лавка",
  "Transform": {
    "scaleX": 1,
    "scaleY": 1,
    "scaleZ": 1
  }
}
