{
  "CardID": 6630100,
  "CustomDeck": {
    "66301": {
      "BackIsHidden": true,
      "BackURL": "https://steamusercontent-a.akamaihd.net/ugc/2342503777940352139/A2D42E7E5C43D045D72CE5CFC907E4F886C8C690/",
      "FaceURL": "https://steamusercontent-a.akamaihd.net/ugc/25441083934057515/F1F3B3B054460BF094593F142420FCE91D540F52/",
      "NumHeight": 1,
      "NumWidth": 1,
      "Type": 0,
      "UniqueBack": false
    }
  },
  "GMNotes_path": "BaldursGateIII.995e96/5ePlayerCards.2c07bb/Camel.ad2d90.gmnotes",
  "GUID": "ad2d90",
  "Name": "Card",
  "Nickname": "Camel",
  "Tags": [
    "Asset",
    "PlayerCard"
  ],
  "Transform": {
    "rotY": 270,
    "scaleX": 1,
    "scaleY": 1,
    "scaleZ": 1
  }
}
