{
  "ContainedObjects_order": [
    "ABalefulWelcome.ff3b62",
    "ABalefulWelcome.ff3b62",
    "BeyondtheVeil.d56ff7",
    "BeyondtheVeil.d56ff7",
    "BeyondtheVeil.d56ff7",
    "CollapsingReality.ab9229",
    "CollapsingReality.ab9229",
    "CollapsingReality.ab9229",
    "ConglomerationofSpheres.1b1dd5",
    "ConglomerationofSpheres.1b1dd5",
    "DimensionalDoorway.a817e8",
    "EldritchAccord.7c4d15",
    "EldritchAccord.7c4d15",
    "EndlessBridge.5ccf98",
    "EndlessBridge.5ccf98",
    "HauntingRecollections.4edfe1",
    "HauntingRecollections.4edfe1",
    "IndecipherableStairs.e3fba9",
    "InfiniteDoorway.64803b",
    "InfiniteDoorway.64803b",
    "InterstellarTraveler.224e79",
    "InterstellarTraveler.224e79",
    "InterstellarTraveler.224e79",
    "PrismaticCascade.8100cf",
    "PrismaticCascade.8100cf",
    "ServantoftheLurker.919fa0",
    "StepsofYhagharl.c704c2",
    "TearThroughSpace.788a8c",
    "TearThroughSpace.788a8c",
    "TearThroughSpace.788a8c",
    "TearThroughSpace.788a8c",
    "ToweringLuminosity.10b92f",
    "UnstableVortex.e3fba9",
    "VassaloftheLurker.a9e3e2",
    "VassaloftheLurker.a9e3e2",
    "VastExpanse.9bf115",
    "VastExpanse.9bf115",
    "VastExpanse.9bf115",
    "VisionsofFuturesPast.42d459",
    "VisionsofFuturesPast.42d459",
    "VisionsofFuturesPast.42d459",
    "Wormhole.bed20e",
    "Wormhole.bed20e",
    "YithianStarseeker.8f9f0a",
    "YithianStarseeker.8f9f0a"
  ],
  "ContainedObjects_path": "EncounterDeck.726813",
  "CustomDeck": {
    "2328": {
      "BackIsHidden": true,
      "BackURL": "https://steamusercontent-a.akamaihd.net/ugc/2342503777940351785/F64D8EFB75A9E15446D24343DA0A6EEF5B3E43DB/",
      "FaceURL": "https://steamusercontent-a.akamaihd.net/ugc/782999241295993974/70871F727ABBAB3DB22003051B5E1FBF8999AEEB/",
      "NumHeight": 7,
      "NumWidth": 10,
      "Type": 0,
      "UniqueBack": false
    },
    "2330": {
      "BackIsHidden": true,
      "BackURL": "https://steamusercontent-a.akamaihd.net/ugc/2342503777940351785/F64D8EFB75A9E15446D24343DA0A6EEF5B3E43DB/",
      "FaceURL": "https://steamusercontent-a.akamaihd.net/ugc/782999241296009359/3EF850792428E467A4475333CCBBF6E6B5975186/",
      "NumHeight": 7,
      "NumWidth": 10,
      "Type": 0,
      "UniqueBack": false
    }
  },
  "DeckIDs": [
    233042,
    233042,
    232811,
    232811,
    232811,
    233020,
    233020,
    233020,
    232830,
    232830,
    233017,
    233052,
    233052,
    233015,
    233015,
    233041,
    233041,
    233038,
    233043,
    233043,
    233018,
    233018,
    233018,
    233014,
    233014,
    232831,
    233016,
    233013,
    233013,
    233013,
    233013,
    233039,
    233040,
    233051,
    233051,
    233022,
    233022,
    233022,
    232810,
    232810,
    232810,
    233021,
    233021,
    233019,
    233019
  ],
  "GMNotes": "",
  "GUID": "726813",
  "Hands": false,
  "HideWhenFaceDown": false,
  "Name": "Deck",
  "Nickname": "Encounter Deck",
  "Transform": {
    "posX": -3.928,
    "posY": 1.821,
    "posZ": 5.757,
    "rotX": 0,
    "rotY": 270,
    "rotZ": 180,
    "scaleX": 1,
    "scaleY": 1,
    "scaleZ": 1
  }
}
