{
  "CardID": 157700,
  "CustomDeck": {
    "1577": {
      "BackIsHidden": true,
      "BackURL": "https://steamusercontent-a.akamaihd.net/ugc/2342503777940351785/F64D8EFB75A9E15446D24343DA0A6EEF5B3E43DB/",
      "FaceURL": "https://www.dropbox.com/scl/fi/yaebxgc6fkq730lxu2iv0/39e1db72-9a9c-4751-b179-44ebecc17c82-Front-391_07_Enemy_Valentino-Rivas-resolution-300-compressionquality-1.00-bleed-0.0-Front.png?rlkey=2bj1d7cc96qgwbiacy5sb6rwu&raw=1&cachebust=1759111565360",
      "NumHeight": 1,
      "NumWidth": 1,
      "Type": 0
    }
  },
  "Description": "Wealthy Philanthropist",
  "GMNotes_path": "UnofficialReturntoTheScarletKeys.300fcd/99C_SecretsoftheLodge.e00283/99C_SecretsoftheLodge-Portrait.e00289/ValentinoRivas.e00290.gmnotes",
  "GUID": "e00290",
  "Name": "Card",
  "Nickname": "Valentino Rivas",
  "Tags": [
    "ScenarioCard"
  ],
  "Transform": {
    "rotY": 270,
    "scaleX": 1,
    "scaleY": 1,
    "scaleZ": 1
  }
}
