{
  "CardID": 11002,
  "CustomDeck": {
    "110": {
      "BackIsHidden": true,
      "BackURL": "https://steamusercontent-a.akamaihd.net/ugc/16182093995789061259/E6A463B94B403DF43BB2803A06749289FA73C253/",
      "FaceURL": "https://steamusercontent-a.akamaihd.net/ugc/9322725927274834774/1247878FE665217ED4D6C70088E5DF154296C65D/",
      "NumHeight": 3,
      "NumWidth": 10,
      "Type": 0,
      "UniqueBack": true
    }
  },
  "Description": "Nie tak odległa przyszłość",
  "GMNotes": "{\"id\":\"05140\"}",
  "GUID": "pl_05140",
  "HideWhenFaceDown": true,
  "Name": "Card",
  "Nickname": "Nieznane miejsca",
  "Transform": {
    "rotY": 270,
    "scaleX": 1,
    "scaleY": 1,
    "scaleZ": 1
  }
}
