{
  "AltLookAngle": {
    "x": 0,
    "y": 0,
    "z": 0
  },
  "Autoraise": true,
  "CardID": 565520,
  "ColorDiffuse": {
    "b": 0.71324,
    "g": 0.71324,
    "r": 0.71324
  },
  "CustomDeck": {
    "5655": {
      "BackIsHidden": true,
      "BackURL": "https://steamusercontent-a.akamaihd.net/ugc/1461933361191993988/FE126C3E21593398897E3C691A0AEA8D9B73A614/",
      "FaceURL": "https://steamusercontent-a.akamaihd.net/ugc/1746813422553218186/31EA4924FA3B5ECEE918640CFAE755EC6BD288AC/",
      "NumHeight": 4,
      "NumWidth": 6,
      "Type": 0,
      "UniqueBack": false
    }
  },
  "Description": "",
  "DragSelectable": true,
  "GMNotes_path": "CyclopeanFoundations.169eb9/4CrumblingMasonry.a4139a/EncounterDeck.e27051/CorneredRat.b2fbec.gmnotes",
  "GUID": "b2fbec",
  "Grid": true,
  "GridProjection": false,
  "Hands": true,
  "HideWhenFaceDown": true,
  "IgnoreFoW": false,
  "LayoutGroupSortIndex": 0,
  "Locked": false,
  "LuaScript": "",
  "LuaScriptState": "",
  "MeasureMovement": false,
  "Name": "Card",
  "Nickname": "Cornered Rat",
  "SidewaysCard": false,
  "Snap": true,
  "Sticky": true,
  "Tags": [
    "ScenarioCard"
  ],
  "Tooltip": true,
  "Transform": {
    "posX": -54.744,
    "posY": 1.378,
    "posZ": -63.325,
    "rotX": 0,
    "rotY": 270,
    "rotZ": 180,
    "scaleX": 1,
    "scaleY": 1,
    "scaleZ": 1
  },
  "Value": 0,
  "XmlUI": ""
}
