{
  "AltLookAngle": {
    "x": 0,
    "y": 0,
    "z": 0
  },
  "Autoraise": true,
  "CardID": 133100,
  "ColorDiffuse": {
    "b": 0.71324,
    "g": 0.71324,
    "r": 0.71324
  },
  "CustomDeck": {
    "1331": {
      "BackIsHidden": true,
      "BackURL": "https://steamusercontent-a.akamaihd.net/ugc/13963584991420426388/3599B61013D4A9D85282818F1C443E70A70FEF7B/",
      "FaceURL": "https://steamusercontent-a.akamaihd.net/ugc/17730844292635277693/E70B183E3F5B3EB137DD4D6FF22C31E16CA3BCB1/",
      "NumHeight": 1,
      "NumWidth": 1,
      "Type": 0,
      "UniqueBack": true
    }
  },
  "Description": "",
  "DragSelectable": true,
  "GMNotes_path": "RiseRaptureRise.412e0a/8TearintheCosmos.3c4bb0/Deck.cc7291/RealityMending.e001b9.gmnotes",
  "GUID": "e001b9",
  "Grid": true,
  "GridProjection": false,
  "Hands": true,
  "HideWhenFaceDown": true,
  "IgnoreFoW": false,
  "LayoutGroupSortIndex": 0,
  "Locked": false,
  "LuaScript": "",
  "LuaScriptState": "",
  "MeasureMovement": false,
  "Name": "Card",
  "Nickname": "...Reality Mending",
  "SidewaysCard": false,
  "Snap": true,
  "Sticky": true,
  "Tags": [
    "ScenarioCard"
  ],
  "Tooltip": true,
  "Transform": {
    "posX": -2.935,
    "posY": 1.598,
    "posZ": -5.053,
    "rotX": 0,
    "rotY": 270,
    "rotZ": 0,
    "scaleX": 0.71,
    "scaleY": 1,
    "scaleZ": 0.71
  },
  "Value": 0,
  "XmlUI": ""
}
