{
  "ContainedObjects_order": [
    "EndlessWeaving.785613",
    "EndlessWeaving.785613",
    "CryptChill.16d6d6",
    "SickeningWebs.09c755",
    "CaughtinaWeb.d9386a",
    "WilloftheSpider-Mother.50e06a",
    "Web-Spinner.e634db",
    "Web-Spinner.e634db",
    "SickeningWebs.09c755",
    "SwarmofSpiders.127543",
    "CaughtinaWeb.d9386a",
    "GreyWeaver.621de5",
    "CaughtinaWeb.d9386a",
    "AncientEvils.6e7cb8",
    "Web-Spinner.e634db",
    "AncientEvils.6e7cb8",
    "AncientEvils.6e7cb8",
    "SpiderofLeng.0f9c1e",
    "ObscuringFog.50e716",
    "GreyWeaver.621de5",
    "WilloftheSpider-Mother.50e06a",
    "CryptChill.16d6d6",
    "SwarmofSpiders.127543",
    "ObscuringFog.50e716",
    "EndlessWeaving.785613",
    "SwarmofSpiders.127543"
  ],
  "ContainedObjects_path": "EncounterDeck.aec151",
  "CustomDeck": {
    "100": {
      "BackIsHidden": true,
      "BackURL": "https://steamusercontent-a.akamaihd.net/ugc/2342503777940351785/F64D8EFB75A9E15446D24343DA0A6EEF5B3E43DB/",
      "FaceURL": "https://steamusercontent-a.akamaihd.net/ugc/13243700374285212184/EA0A1926B70F720CDBC4EDC375FE76BD22E17389/",
      "NumHeight": 4,
      "NumWidth": 7,
      "Type": 0
    },
    "2346": {
      "BackIsHidden": true,
      "BackURL": "https://steamusercontent-a.akamaihd.net/ugc/2342503777940351785/F64D8EFB75A9E15446D24343DA0A6EEF5B3E43DB/",
      "FaceURL": "https://steamusercontent-a.akamaihd.net/ugc/1016065725025770470/7C77423FFA657FB6B5937C80D6813C24E2D0E88C/",
      "NumHeight": 7,
      "NumWidth": 10,
      "Type": 0
    },
    "2741": {
      "BackIsHidden": true,
      "BackURL": "https://steamusercontent-a.akamaihd.net/ugc/2342503777940351785/F64D8EFB75A9E15446D24343DA0A6EEF5B3E43DB/",
      "FaceURL": "https://steamusercontent-a.akamaihd.net/ugc/778493383646802545/EF89145CA7EEC1746A59CCBDDEE52526997C5DED/",
      "NumHeight": 7,
      "NumWidth": 10,
      "Type": 0
    }
  },
  "DeckIDs": [
    234644,
    234644,
    10010,
    274128,
    234643,
    274110,
    234641,
    234641,
    274128,
    274127,
    234643,
    274109,
    234643,
    10009,
    234641,
    10009,
    10009,
    274126,
    10011,
    274109,
    274110,
    10010,
    274127,
    10011,
    234644,
    274127
  ],
  "GUID": "aec151",
  "Hands": false,
  "Name": "Deck",
  "Nickname": "Encounter Deck",
  "Transform": {
    "rotY": 270,
    "rotZ": 180,
    "scaleX": 1,
    "scaleY": 1,
    "scaleZ": 1
  }
}
