{
  "AltLookAngle": {
    "x": 0,
    "y": 0,
    "z": 0
  },
  "Autoraise": true,
  "CardID": 279402,
  "ColorDiffuse": {
    "b": 0.71324,
    "g": 0.71324,
    "r": 0.71324
  },
  "CustomDeck": {
    "2794": {
      "BackIsHidden": true,
      "BackURL": "https://steamusercontent-a.akamaihd.net/ugc/2001337710391776939/CAEF692DB6FBAA31B5CA3CA1221EB4BC962AD5EF/",
      "FaceURL": "https://steamusercontent-a.akamaihd.net/ugc/2001337710391776346/C7164F9DC4769043AC434E02AD632A7D1980C6A2/",
      "NumHeight": 2,
      "NumWidth": 2,
      "Type": 0,
      "UniqueBack": true
    }
  },
  "Description": "Piper at the Gates of Dawn",
  "DragSelectable": true,
  "GMNotes_path": "CircusExMortisCampaignExpansion.93b8cb/5PiperattheGatesofDawn.abaaec/Scenario.56dbcc.gmnotes",
  "GUID": "56dbcc",
  "Grid": true,
  "GridProjection": false,
  "Hands": true,
  "HideWhenFaceDown": false,
  "IgnoreFoW": false,
  "LayoutGroupSortIndex": 0,
  "Locked": false,
  "LuaScript": "",
  "LuaScriptState": "",
  "MeasureMovement": false,
  "Name": "Card",
  "Nickname": "Scenario",
  "SidewaysCard": false,
  "Snap": true,
  "Sticky": true,
  "Tags": [
    "ScenarioCard"
  ],
  "Tooltip": true,
  "Transform": {
    "posX": -3.85,
    "posY": 1.597,
    "posZ": -10.388,
    "rotX": 0,
    "rotY": 270,
    "rotZ": 0,
    "scaleX": 1,
    "scaleY": 1,
    "scaleZ": 1
  },
  "Value": 0,
  "XmlUI": ""
}
