{
  "CardID": 462703,
  "CustomDeck": {
    "4627": {
      "BackIsHidden": true,
      "BackURL": "https://i.imgur.com/EYOkos0.jpg",
      "FaceURL": "https://i.imgur.com/SfjqkU0.jpg",
      "NumHeight": 2,
      "NumWidth": 10,
      "Type": 0,
      "UniqueBack": true
    }
  },
  "GMNotes": "{\"id\": \"02045\"\n}",
  "GUID": "92ab32",
  "Name": "Card",
  "Nickname": "Después de clase",
  "SidewaysCard": true,
  "Transform": {
    "rotY": 90,
    "scaleX": 1,
    "scaleY": 1,
    "scaleZ": 1
  }
}
