{
  "CardID": 2897400,
  "CustomDeck": {
    "28974": {
      "BackIsHidden": true,
      "BackURL": "https://steamusercontent-a.akamaihd.net/ugc/13387945871146636995/DF828BE49A25EA79FB0AE5E90E8C8856BE92356A/",
      "FaceURL": "https://steamusercontent-a.akamaihd.net/ugc/13724398982182972511/CE27DA9B23C0EFBE9A0D3B9B9835027F50084030/",
      "NumHeight": 1,
      "NumWidth": 8,
      "Type": 0,
      "UniqueBack": true
    }
  },
  "GMNotes": "{\"id\": \"52054\"}",
  "GUID": "365985",
  "Name": "Card",
  "Nickname": "重返黑星升起",
  "Transform": {
    "rotY": 180,
    "rotZ": 180,
    "scaleX": 1,
    "scaleY": 1,
    "scaleZ": 1
  }
}