{
  "CardID": 562500,
  "CustomDeck": {
    "5625": {
      "BackIsHidden": true,
      "BackURL": "https://steamusercontent-a.akamaihd.net/ugc/2342503777940351785/F64D8EFB75A9E15446D24343DA0A6EEF5B3E43DB/",
      "FaceURL": "https://res.cloudinary.com/dnyyxgsfq/image/upload/v1771170617/AH_LCG_Core_Campaign/01182_front.jpg",
      "NumHeight": 1,
      "NumWidth": 1,
      "Type": 0,
      "UniqueBack": true
    }
  },
  "GMNotes": "{\n  \"id\": \"01182\"\n}",
  "GUID": "9074ed",
  "Name": "CardCustom",
  "Nickname": "Sny o R'lyeh",
  "Transform": {
    "rotY": 270,
    "scaleX": 1,
    "scaleY": 1,
    "scaleZ": 1
  }
}
