{
  "CardID": 572300,
  "CustomDeck": {
    "5723": {
      "BackIsHidden": true,
      "BackURL": "https://steamusercontent-a.akamaihd.net/ugc/1732171226993770932/4616103F2AC98D5481C789D47504C90DC0D2FCF2/",
      "FaceURL": "https://steamusercontent-a.akamaihd.net/ugc/1732171226993770784/8CF613E2B5749D0B709544031A48D0066222AECE/",
      "NumHeight": 1,
      "NumWidth": 1,
      "Type": 0
    }
  },
  "GMNotes_path": "DarkMatter.d713f4/LostQuantum.c29a78/LostQuantum.634def.gmnotes",
  "GUID": "634def",
  "Name": "CardCustom",
  "Nickname": "Lost Quantum",
  "Transform": {
    "rotY": 270,
    "scaleX": 1,
    "scaleY": 1,
    "scaleZ": 1
  }
}
