{
  "CardID": 267702,
  "CustomDeck": {
    "2677": {
      "BackIsHidden": true,
      "BackURL": "https://steamusercontent-a.akamaihd.net/ugc/2342503777940351785/F64D8EFB75A9E15446D24343DA0A6EEF5B3E43DB/",
      "FaceURL": "https://steamusercontent-a.akamaihd.net/ugc/2001337710383857827/6F76854F02EAB5E9634360F8E255AEC34B20059C/",
      "NumHeight": 2,
      "NumWidth": 2,
      "Type": 0
    }
  },
  "GMNotes_path": "Jumanji.5bd588/4ForceofNature.8a3606/JumanjiSets.44a268/EarthquakeEncounterSet.edc24c/CollapsingGround.ced50d.gmnotes",
  "GUID": "ced50d",
  "Name": "Card",
  "Nickname": "Collapsing Ground",
  "Tags": [
    "ScenarioCard"
  ],
  "Transform": {
    "rotY": 270,
    "scaleX": 1,
    "scaleY": 1,
    "scaleZ": 1
  }
}
