{
  "CardID": 105000,
  "CustomDeck": {
    "1050": {
      "BackIsHidden": true,
      "BackURL": "https://steamusercontent-a.akamaihd.net/ugc/2342503777940351785/F64D8EFB75A9E15446D24343DA0A6EEF5B3E43DB/",
      "FaceURL": "https://steamusercontent-a.akamaihd.net/ugc/13708169340490557113/CF585BF1844408674188E849B47E7E5F654A3F17/",
      "NumHeight": 1,
      "NumWidth": 1,
      "Type": 0,
      "UniqueBack": false
    }
  },
  "GMNotes_path": "TheWoodsoftheBlackGoat.667111/Set-aside.c329fa/ThousandYoungEncounterSet.66b19a/MothersMilk.e0003f.gmnotes",
  "GUID": "e0003f",
  "Name": "Card",
  "Nickname": "Mother's Milk",
  "Tags": [
    "ScenarioCard"
  ],
  "Transform": {
    "posX": 21.164,
    "posY": 1.495,
    "posZ": -26.866,
    "rotX": 0,
    "rotY": 270,
    "rotZ": 0,
    "scaleX": 1,
    "scaleY": 1,
    "scaleZ": 1
  }
}
