{
  "ContainedObjects_order": [
    "OuterFields.57e491",
    "OuterFields.d02423",
    "OuterFields.d66562",
    "OuterFields.6a2604",
    "OuterFields.a107d9"
  ],
  "ContainedObjects_path": "OuterFields.2193c3",
  "CustomDeck": {
    "5401": {
      "BackIsHidden": true,
      "BackURL": "https://steamusercontent-a.akamaihd.net/ugc/2453969772006055371/DEA899F42BF11E62836A1F08EFAAB2137738CDAB/",
      "FaceURL": "https://steamusercontent-a.akamaihd.net/ugc/2453969772006054449/E3F361172C58FB357238946B925502E17BB411F3/",
      "NumHeight": 6,
      "NumWidth": 9,
      "Type": 0,
      "UniqueBack": true
    }
  },
  "DeckIDs": [
    540126,
    540127,
    540128,
    540129,
    540130
  ],
  "GMNotes": "",
  "GUID": "2193c3",
  "Hands": false,
  "Name": "Deck",
  "Nickname": "Outer Fields",
  "Tags": [
    "Location",
    "ScenarioCard"
  ],
  "Transform": {
    "posX": -30.24,
    "posY": 1.565,
    "posZ": 3.83,
    "rotX": 0,
    "rotY": 270,
    "rotZ": 0,
    "scaleX": 1,
    "scaleY": 1,
    "scaleZ": 1
  }
}
