{
  "CardID": 853300,
  "CustomDeck": {
    "8533": {
      "BackIsHidden": true,
      "BackURL": "https://steamusercontent-a.akamaihd.net/ugc/18140641997205643749/7306CF0FC5B11DBD2FF2EC6C5EA53D80BF1F845F/",
      "FaceURL": "https://steamusercontent-a.akamaihd.net/ugc/13188774012195754948/92AAD28CAD6697309C7D3331446F6A32347C3846/",
      "NumHeight": 1,
      "NumWidth": 1,
      "Type": 0,
      "UniqueBack": true
    }
  },
  "Description": "Silencio en plató",
  "GMNotes": "{\n  \"id\": \"72008\"\n}",
  "GUID": "c93e05",
  "Name": "CardCustom",
  "Nickname": "Estudio central",
  "Transform": {
    "scaleX": 1,
    "scaleY": 1,
    "scaleZ": 1
  }
}
