{
  "CardID": 870200,
  "CustomDeck": {
    "8702": {
      "BackIsHidden": true,
      "BackURL": "https://res.cloudinary.com/dnyyxgsfq/image/upload/v1772090301/Carcosa_Campaign_Cards/03324_back.jpg",
      "FaceURL": "https://res.cloudinary.com/dnyyxgsfq/image/upload/v1772090299/Carcosa_Campaign_Cards/03324_front.jpg",
      "NumHeight": 1,
      "NumWidth": 1,
      "Type": 0,
      "UniqueBack": true
    }
  },
  "GMNotes": "{\n  \"id\": \"03324\"\n}",
  "GUID": "617d3f",
  "Name": "CardCustom",
  "Nickname": "Król w Łachmanach",
  "SidewaysCard": true,
  "Transform": {
    "scaleX": 1,
    "scaleY": 1,
    "scaleZ": 1
  }
}
