{
  "CardID": 119400,
  "CustomDeck": {
    "1194": {
      "BackIsHidden": true,
      "BackURL": "https://steamusercontent-a.akamaihd.net/ugc/17379895694067152786/EDDB45B2E225883DBDD32F846CABAACC04A45481/",
      "FaceURL": "https://steamusercontent-a.akamaihd.net/ugc/16900474343137673361/1633614F3285140C54F3A84D10CF5C2EB0124BC9/",
      "NumHeight": 1,
      "NumWidth": 1,
      "Type": 0,
      "UniqueBack": true
    }
  },
  "GMNotes_path": "RiseRaptureRise.412e0a/5MarchHareBlackDream.9577e7/5MarchHare.e64313/Deck.d95846/CaughtintheSpotlightvI.e000fd.gmnotes",
  "GUID": "e000fd",
  "Hands": false,
  "Name": "Card",
  "Nickname": "Caught in the Spotlight  (v. I)",
  "Tags": [
    "ScenarioCard"
  ],
  "Transform": {
    "rotY": 270,
    "scaleX": 0.71,
    "scaleY": 1,
    "scaleZ": 0.71
  }
}
