{
  "AltLookAngle": {
    "x": 0,
    "y": 0,
    "z": 0
  },
  "Autoraise": true,
  "CardID": 591118,
  "ColorDiffuse": {
    "b": 0.71324,
    "g": 0.71324,
    "r": 0.71324
  },
  "CustomDeck": {
    "5887": {
      "BackIsHidden": true,
      "BackURL": "https://steamusercontent-a.akamaihd.net/ugc/1938266093883144543/321B70E2509F1852398770FBCEDC5FBAF016DA3D/",
      "FaceURL": "https://steamusercontent-a.akamaihd.net/ugc/1938266093883143515/90ED945CAC67945F969BB710BA6E58FF780F0CA3/",
      "NumHeight": 4,
      "NumWidth": 6,
      "Type": 0,
      "UniqueBack": true
    }
  },
  "Description": "Monster. Geist. Elite.",
  "DragSelectable": true,
  "GMNotes_path": "TheScarletKeys.300fcc/File46-QShadesofSuffering.c98a8a/SlainForemen.870b21/SlainForeman.60db40.gmnotes",
  "GUID": "60db40",
  "Grid": true,
  "GridProjection": false,
  "Hands": true,
  "HideWhenFaceDown": true,
  "IgnoreFoW": false,
  "LayoutGroupSortIndex": 0,
  "Locked": false,
  "LuaScript": "",
  "LuaScriptState": "",
  "MeasureMovement": false,
  "Name": "Card",
  "Nickname": "Slain Foreman",
  "SidewaysCard": false,
  "Snap": true,
  "Sticky": true,
  "Tags": [
    "ScenarioCard"
  ],
  "Tooltip": true,
  "Transform": {
    "posX": -3.091,
    "posY": 1.596,
    "posZ": 13.497,
    "rotX": 0,
    "rotY": 270,
    "rotZ": 0,
    "scaleX": 1,
    "scaleY": 1,
    "scaleZ": 1
  },
  "Value": 0,
  "XmlUI": ""
}