{
  "CardID": 266500,
  "CustomDeck": {
    "2665": {
      "BackIsHidden": true,
      "BackURL": "https://steamusercontent-a.akamaihd.net/ugc/12305459845855451046/3F3A18A8F40680D27923484448CF383A595B93D4/",
      "FaceURL": "https://steamusercontent-a.akamaihd.net/ugc/16863378468057724918/64A084957C5B35C76876A28E573E53C1B78B6673/",
      "NumHeight": 7,
      "NumWidth": 10,
      "Type": 0,
      "UniqueBack": true
    }
  },
  "Description": "Возвращение.",
  "GMNotes": "{\"id\":\"52014\"}",
  "GUID": "e2dab9",
  "HideWhenFaceDown": false,
  "Name": "Card",
  "Nickname": "Дайте занавес. Возвращение",
  "Transform": {
    "posX": 39.697,
    "posY": 2.779,
    "posZ": 30.894,
    "rotX": 0,
    "rotY": 270,
    "rotZ": 0,
    "scaleX": 1,
    "scaleY": 1,
    "scaleZ": 1
  }
}
