{
  "CardID": 265120,
  "CustomDeck": {
    "2651": {
      "BackIsHidden": true,
      "BackURL": "https://steamusercontent-a.akamaihd.net/ugc/2342503777940351785/F64D8EFB75A9E15446D24343DA0A6EEF5B3E43DB/",
      "FaceURL": "https://i.imgur.com/URbV3ol.jpg",
      "NumHeight": 4,
      "NumWidth": 6,
      "Type": 0,
      "UniqueBack": false
    }
  },
  "Description": "Hazard.",
  "GMNotes_path": "TheLabyrinthsofLunacy.4c173f/EpicGroupB.c7c4c1/EncounterDeck.397fe8/ParadoxEffect.1f26ea.gmnotes",
  "GUID": "1f26ea",
  "Name": "Card",
  "Nickname": "Paradox Effect",
  "Tags": [
    "ScenarioCard"
  ],
  "Transform": {
    "posX": 100.134,
    "posY": 1.552,
    "posZ": 0.456,
    "rotX": 0,
    "rotY": 270,
    "rotZ": 0,
    "scaleX": 1,
    "scaleY": 1,
    "scaleZ": 1
  }
}
