{
  "ContainedObjects_order": [
    "DeepOneAmbush.b5d1d4",
    "DeepOneAmbush.35d198",
    "ElderDeepOne.83b380",
    "DeepOneThrall.1991f1",
    "DeepOneThrall.d862ec",
    "Domination.60e7d9",
    "OppressiveInfluence.817378",
    "OppressiveInfluence.d18fec",
    "Cthulhufhtagn.c72077",
    "Cthulhufhtagn.069951",
    "DrawntoDarkness.28b3d4",
    "DrawntoDarkness.af667e",
    "DrawntoDarkness.28b3d4",
    "TorturedVisions.fad46e",
    "TorturedVisions.fcbb89",
    "TorturedVisions.fad46e",
    "YoungDeepOne.cfd69a",
    "YoungDeepOne.ab3719",
    "DreamsofRlyeh.47ed9e",
    "DreamsofRlyeh.796db7"
  ],
  "ContainedObjects_path": "EncounterDeck.c59450",
  "CustomDeck": {
    "2317": {
      "BackIsHidden": true,
      "BackURL": "https://steamusercontent-a.akamaihd.net/ugc/2342503777940351785/F64D8EFB75A9E15446D24343DA0A6EEF5B3E43DB/",
      "FaceURL": "https://steamusercontent-a.akamaihd.net/ugc/775106514377430057/E4E5A51434CEF23EF5D04A104F352520304AA550/",
      "NumHeight": 7,
      "NumWidth": 10,
      "Type": 0,
      "UniqueBack": false
    },
    "2668": {
      "BackIsHidden": true,
      "BackURL": "https://steamusercontent-a.akamaihd.net/ugc/2342503777940351785/F64D8EFB75A9E15446D24343DA0A6EEF5B3E43DB/",
      "FaceURL": "https://steamusercontent-a.akamaihd.net/ugc/62595225072210519/EEFB1983C0F9A1B9F4F03BDAFA1404E01EF06BAD/",
      "NumHeight": 4,
      "NumWidth": 8,
      "Type": 0,
      "UniqueBack": false
    }
  },
  "DeckIDs": [
    266827,
    266827,
    266826,
    266825,
    266825,
    266822,
    266821,
    266821,
    266820,
    266820,
    266829,
    266829,
    266829,
    266828,
    266828,
    266828,
    231734,
    231734,
    231735,
    231735
  ],
  "GUID": "c59450",
  "Hands": false,
  "Name": "Deck",
  "Nickname": "Encounter Deck",
  "Transform": {
    "posX": -3.851,
    "posY": 1.7,
    "posZ": 5.72,
    "rotX": 0,
    "rotY": 270,
    "rotZ": 180,
    "scaleX": 1,
    "scaleY": 1,
    "scaleZ": 1
  }
}
