{
  "Bag": {
    "Order": 0
  },
  "ColorDiffuse": {
    "b": 0.168,
    "g": 0.701,
    "r": 0.192
  },
  "ContainedObjects_order": [
    "ColdStreak.a90a1a",
    "JohnnyValone.02dbfd",
    "TheSyndicate.57261f"
  ],
  "ContainedObjects_path": "RivalTheSyndicate.af62ff",
  "GMNotes": "",
  "GUID": "af62ff",
  "Hands": false,
  "HideWhenFaceDown": false,
  "MaterialIndex": -1,
  "MeshIndex": -1,
  "Name": "Bag",
  "Nickname": "Rival: The Syndicate",
  "Transform": {
    "posX": 15.969,
    "posY": 3.371,
    "posZ": 66.832,
    "rotX": 2,
    "rotY": 0,
    "rotZ": 0,
    "scaleX": 1,
    "scaleY": 1,
    "scaleZ": 1
  }
}
