{
  "CardID": 132400,
  "CustomDeck": {
    "1324": {
      "BackIsHidden": true,
      "BackURL": "https://steamusercontent-a.akamaihd.net/ugc/11072133988058081858/3C2178A91373F7B45CF32DE13D20ADD85D38E3E7/",
      "FaceURL": "https://steamusercontent-a.akamaihd.net/ugc/17379594935918736846/6E0E2370E4D3D8F37C6357E67534876E5F70F118/",
      "NumHeight": 1,
      "NumWidth": 1,
      "Type": 0,
      "UniqueBack": true
    }
  },
  "GMNotes_path": "RiseRaptureRise.412e0a/7TerrorintheDeep.041554/7TerrorintheDeepvII.548d89/MedicalPavilionRuins.e001af.gmnotes",
  "GUID": "e001af",
  "Hands": false,
  "HideWhenFaceDown": false,
  "Name": "Card",
  "Nickname": "Medical Pavilion Ruins",
  "Tags": [
    "Location",
    "ScenarioCard"
  ],
  "Transform": {
    "rotY": 270,
    "rotZ": 180,
    "scaleX": 1,
    "scaleY": 1,
    "scaleZ": 1
  }
}
