{
  "CardID": 233304,
  "CustomDeck": {
    "2333": {
      "BackIsHidden": true,
      "BackURL": "https://steamusercontent-a.akamaihd.net/ugc/2342503777940351785/F64D8EFB75A9E15446D24343DA0A6EEF5B3E43DB/",
      "FaceURL": "https://steamusercontent-a.akamaihd.net/ugc/775106514377430057/E4E5A51434CEF23EF5D04A104F352520304AA550/",
      "NumHeight": 7,
      "NumWidth": 10,
      "Type": 0,
      "UniqueBack": false
    }
  },
  "GMNotes_path": "ThePathtoCarcosa.aca04c/5APhantomofTruth.bd4167/DoubtorEqual.5358e2/AddtoEncounterDeck.90bef0/FalseLead.2ceae2.gmnotes",
  "GUID": "2ceae2",
  "Name": "Card",
  "Nickname": "False Lead",
  "Tags": [
    "ScenarioCard"
  ],
  "Transform": {
    "posX": -54.425,
    "posY": 1.868,
    "posZ": 29.502,
    "rotX": 357,
    "rotY": 270,
    "rotZ": 0,
    "scaleX": 1,
    "scaleY": 1,
    "scaleZ": 1
  }
}
