{
  "ContainedObjects_order": [
    "TheGuardianSpirit.296816",
    "UndertheLights.6ccc29",
    "MistySteps.f74d0a"
  ],
  "ContainedObjects_path": "ActDeck.18a95b",
  "CustomDeck": {
    "2662": {
      "BackIsHidden": true,
      "BackURL": "https://i.imgur.com/2WwfSEF.png",
      "FaceURL": "https://i.imgur.com/7qG1rWK.jpg",
      "NumHeight": 7,
      "NumWidth": 10,
      "Type": 0,
      "UniqueBack": true
    }
  },
  "DeckIDs": [
    266202,
    266201,
    266200
  ],
  "GUID": "18a95b",
  "Hands": false,
  "Name": "Deck",
  "Nickname": "Act Deck",
  "SidewaysCard": true,
  "Transform": {
    "rotX": 0,
    "rotY": 180,
    "rotZ": 0,
    "scaleX": 1,
    "scaleY": 1,
    "scaleZ": 1
  }
}
