{
  "CardID": 232101,
  "CustomDeck": {
    "2321": {
      "BackIsHidden": true,
      "BackURL": "https://steamusercontent-a.akamaihd.net/ugc/2342503777940352139/A2D42E7E5C43D045D72CE5CFC907E4F886C8C690/",
      "FaceURL": "https://steamusercontent-a.akamaihd.net/ugc/13372923241944590926/0FB2077820643A56B64590E62E03AFED2C6DB83C/",
      "NumHeight": 5,
      "NumWidth": 5,
      "Type": 0,
      "UniqueBack": false
    }
  },
  "Description": "Дух. Заклинание. Благословенное.",
  "GMNotes": "{\n  \"id\": \"07153\"\n}",
  "GUID": "92c295",
  "LuaScript": "require(\"playercards/cards/RadiantSmite1\")",
  "Name": "Card",
  "Nickname": "Лучистый залп (1)",
  "Transform": {
    "posX": 9.151,
    "posY": 4.13,
    "posZ": -16.727,
    "rotX": 0,
    "rotY": 270,
    "rotZ": 0,
    "scaleX": 1,
    "scaleY": 1,
    "scaleZ": 1
  }
}
