{
  "ContainedObjects_order": [
    "CuttheThread.bf1645",
    "CuttheThread.bb7ca9",
    "WitchesSabbath.e00002",
    "WitchesSabbath.253a58",
    "EvilEye.9c34fb",
    "EvilEye.471295"
  ],
  "ContainedObjects_path": "Deck.9a8645",
  "CustomDeck": {
    "1000": {
      "BackIsHidden": true,
      "BackURL": "https://steamusercontent-a.akamaihd.net/ugc/2342503777940351785/F64D8EFB75A9E15446D24343DA0A6EEF5B3E43DB/",
      "FaceURL": "https://steamusercontent-a.akamaihd.net/ugc/13454047477715506180/DC145C3BC7B8ACA24CF561C04EE40C088014E551/",
      "NumHeight": 1,
      "NumWidth": 1,
      "Type": 0
    },
    "1001": {
      "BackIsHidden": true,
      "BackURL": "https://steamusercontent-a.akamaihd.net/ugc/2342503777940351785/F64D8EFB75A9E15446D24343DA0A6EEF5B3E43DB/",
      "FaceURL": "https://steamusercontent-a.akamaihd.net/ugc/14502667519085045471/31F415224E88BD95960EF4DBBCC6689452BBA828/",
      "NumHeight": 1,
      "NumWidth": 1,
      "Type": 0
    },
    "3217": {
      "BackIsHidden": true,
      "BackURL": "https://steamusercontent-a.akamaihd.net/ugc/2342503777940351785/F64D8EFB75A9E15446D24343DA0A6EEF5B3E43DB/",
      "FaceURL": "https://steamusercontent-a.akamaihd.net/ugc/16418029550465385104/E60E805818F81E21657AE01935AF532A8A79ACBC/",
      "NumHeight": 1,
      "NumWidth": 1,
      "Type": 0
    }
  },
  "DeckIDs": [
    321700,
    321700,
    100100,
    100100,
    100000,
    100000
  ],
  "GUID": "9a8645",
  "Hands": false,
  "Name": "Deck",
  "Nickname": "",
  "Tags": [
    "ScenarioCard"
  ],
  "Transform": {
    "rotY": 270,
    "scaleX": 1,
    "scaleY": 1,
    "scaleZ": 1
  }
}
