{
  "AltLookAngle": {
    "x": 0,
    "y": 0,
    "z": 0
  },
  "Autoraise": true,
  "ColorDiffuse": {
    "b": 0.71324,
    "g": 0.71324,
    "r": 0.71324
  },
  "ContainedObjects_order": [
    "HistoricalSociety.4592ee",
    "HistoricalSociety.ffd0fb",
    "HistoricalSociety.aa08d4"
  ],
  "ContainedObjects_path": "GroundFloor.fc0ccf",
  "CustomDeck": {
    "2320": {
      "BackIsHidden": true,
      "BackURL": "https://steamusercontent-a.akamaihd.net/ugc/775107058378685352/22FD056BAF1966FE2D1AC46FC1BF90C1A03A1404/",
      "FaceURL": "https://steamusercontent-a.akamaihd.net/ugc/775107058378686413/C1688C1A909FDC7357EB3EEFADAB1FBD5818BD3E/",
      "NumHeight": 7,
      "NumWidth": 10,
      "Type": 0,
      "UniqueBack": true
    },
    "5554": {
      "BackIsHidden": true,
      "BackURL": "https://steamusercontent-a.akamaihd.net/ugc/1656727981627987825/3F75AF019AA235E62BE016D1294538395F5FD0EC/",
      "FaceURL": "https://steamusercontent-a.akamaihd.net/ugc/1656727981627987175/2D09488350DCAA9D47EC0E02D89F74B4C953B17C/",
      "NumHeight": 2,
      "NumWidth": 3,
      "Type": 0,
      "UniqueBack": true
    }
  },
  "DeckIDs": [
    555403,
    232021,
    232020
  ],
  "Description": "",
  "DragSelectable": true,
  "GMNotes": "",
  "GUID": "fc0ccf",
  "Grid": true,
  "GridProjection": false,
  "Hands": false,
  "HideWhenFaceDown": false,
  "IgnoreFoW": false,
  "LayoutGroupSortIndex": 0,
  "Locked": false,
  "LuaScript": "",
  "LuaScriptState": "",
  "MeasureMovement": false,
  "Name": "Deck",
  "Nickname": "Ground Floor",
  "SidewaysCard": false,
  "Snap": true,
  "Sticky": true,
  "Tooltip": true,
  "Transform": {
    "posX": -30.224,
    "posY": 1.555,
    "posZ": 15.19,
    "rotX": 0,
    "rotY": 270,
    "rotZ": 0,
    "scaleX": 1,
    "scaleY": 1,
    "scaleZ": 1
  },
  "Value": 0,
  "XmlUI": ""
}
